QoreWidgets/__init__.py
QoreWidgets/rc.py
QoreWidgets/__pyside6__/__framelessWindow__/framelessWindow.py
QoreWidgets/__pyside6__/__immersiveTitleBar__/immersiveTitleBar.py
QoreWidgets/__pyside6__/__immersiveTitleBar__/immersiveTitleBarContainer.py
QoreWidgets/__pyside6__/__overlay__/emptyOverlay.py
QoreWidgets/__pyside6__/__overlay__/loadingOverlay.py
QoreWidgets/__pyside6__/__sideTabWidget__/sideTabWidget.py
QoreWidgets-0.2.2.dist-info/LICENSE
QoreWidgets-0.2.2.dist-info/METADATA
QoreWidgets-0.2.2.dist-info/WHEEL
QoreWidgets-0.2.2.dist-info/top_level.txt
QoreWidgets-0.2.2.dist-info/RECORD
