Metadata-Version: 2.1
Name: QoreWidgets
Version: 0.2.2
Summary: Yet another collection of those core widgets for a modern qt application.
Author-email: Dylan <du33169@gmail.com>
License: BSD 3-Clause License
Project-URL: Homepage, https://github.com/du33169/QoreWidgets
Project-URL: Bug Tracker, https://github.com/du33169/QoreWidgets/issues
Requires-Python: >=3.8
License-File: LICENSE
Provides-Extra: pyside6
Requires-Dist: PySide6 ; extra == 'pyside6'
